demos/__init__.py
demos/curvature_refinement.py
demos/demo_bspline.py
demos/demo_periodic_bspline.py
demos/mass_matrices.py
demos/perf_measure.py
demos/t_from_bspl_point.py
pysplines/__init__.py
pysplines/alexpression.py
pysplines/bsplines.py
pysplines/decorators.py
pysplines/example_bspline.py
pysplines/tests/__init__.py
pysplines/tests/test_alexpression.py
pysplines/tests/test_bspline.py
pysplines/tests/test_core_bspline.py
pysplines-0.3.0.dist-info/LICENSE
pysplines-0.3.0.dist-info/METADATA
pysplines-0.3.0.dist-info/WHEEL
pysplines-0.3.0.dist-info/top_level.txt
pysplines-0.3.0.dist-info/RECORD
