Metadata-Version: 2.1
Name: pysplines
Version: 0.3.0
Summary: Tool to create discrete b-splines with surface properties
Home-page: https://github.com/Corwinpro/PySplines
Author: Petr Kungurtsev
License: UNKNOWN
Platform: UNKNOWN
Classifier: Programming Language :: Python :: 3
Classifier: License :: OSI Approved :: MIT License
Classifier: Operating System :: OS Independent
Requires-Python: >=3.6
License-File: LICENSE
Requires-Dist: numpy
Requires-Dist: sympy
Requires-Dist: scipy
